pyoomysql/Column.py
pyoomysql/Database.py
pyoomysql/ProxySQL.py
pyoomysql/Schema.py
pyoomysql/Table.py
pyoomysql/User.py
pyoomysql/__init__.py
pyoomysql/version.py
pyoomysql/util/__init__.py
pyoomysql/util/json.py
pyoomysql/util/sql.py
tests/__init__.py
tests/simple_script.py
pyoomysql-0.3.3.dist-info/LICENSE
pyoomysql-0.3.3.dist-info/METADATA
pyoomysql-0.3.3.dist-info/WHEEL
pyoomysql-0.3.3.dist-info/top_level.txt
pyoomysql-0.3.3.dist-info/RECORD
