Metadata-Version: 2.1
Name: pyoomysql
Version: 0.3.3
Summary: Python Object-Orinted MySQL interface
Home-page: https://gitlab.com/silvarion/python/packages/pyoomysql
Author: Jesus Alejandro Sanchez Davila
Author-email: jsanchez.consultant@gmail.com
Classifier: Programming Language :: Python :: 3
Classifier: License :: OSI Approved :: MIT License
Classifier: Operating System :: OS Independent
Requires-Python: >=3.9
License-File: LICENSE
Requires-Dist: mysql-connector-python
